[{"filament":"PLA Basic","baseColor":"Red","color":"Red","brand":"Bambu","identifier":"10200","activeSpool":"1000","spareSpools":"0"},{"filament":"PLA Basic","baseColor":"Orange","color":"Neon Orange","brand":"Polymaker","identifier":"Panchroma","activeSpool":"800","spareSpools":"0","link":"https://a.co/d/06Jp8Z5Q"},{"filament":"PLA Basic","baseColor":"Yellow","color":"Neon Yellow","brand":"Polymaker","identifier":"Panchroma","activeSpool":"800","spareSpools":"0","link":"https://a.co/d/0i7t5V6V"},{"filament":"PLA Basic","baseColor":"Green","color":"Bambu Green","brand":"Bambu","identifier":"10501","activeSpool":"900","spareSpools":"0"},{"filament":"PLA Basic","baseColor":"Green","color":"Mistletoe Green","brand":"Bambu","identifier":"10502","activeSpool":"600","spareSpools":"0"},{"filament":"PLA Basic","baseColor":"Blue","color":"Cobalt Blue","brand":"Bambu","identifier":"10604","activeSpool":"0","spareSpools":"1"},{"filament":"PLA Basic","baseColor":"Blue","color":"Burnt Titanium","brand":"FLASHFORGE","identifier":"","activeSpool":"1000","spareSpools":"0","link":"https://a.co/d/03NLBAo5"},{"filament":"PLA Basic","baseColor":"Purple","color":"Purple","brand":"Bambu","identifier":"10700","activeSpool":"450","spareSpools":"0"},{"filament":"PLA Basic","baseColor":"Purple","color":"Indigo Purple","brand":"Bambu","identifier":"10701","activeSpool":"0","spareSpools":"1"},{"filament":"PLA Basic","baseColor":"Pink","color":"Hot Pink","brand":"Bambu","identifier":"10204","activeSpool":"900","spareSpools":"0"},{"filament":"PLA Basic","baseColor":"Tan","color":"Beige","brand":"Bambu","identifier":"10201","activeSpool":"0","spareSpools":"1"},{"filament":"PLA Basic","baseColor":"Black","color":"Black","brand":"Bambu","identifier":"10101","activeSpool":"1000","spareSpools":"1"},{"filament":"PLA Basic","baseColor":"Gray","color":"Gray","brand":"Bambu","identifier":"10103","activeSpool":"1000","spareSpools":"0"},{"filament":"PLA Basic","baseColor":"Gray","color":"Silver","brand":"Bambu","identifier":"10102","activeSpool":"900","spareSpools":"0"},{"filament":"PLA Basic","baseColor":"White","color":"Jade White","brand":"Bambu","identifier":"10100","activeSpool":"100","spareSpools":"1"},{"filament":"PLA Basic","baseColor":"Multicolor","color":"Rainbow","brand":"FLASHFORGE","identifier":"","activeSpool":"900","spareSpools":"0","link":"https://a.co/d/0b0uZtIo"},{"filament":"PLA Matte","baseColor":"Red","color":"Dark Red","brand":"Bambu","identifier":"11202","activeSpool":"0","spareSpools":"1"},{"filament":"PLA Matte","baseColor":"Orange","color":"Mandarin Orange","brand":"Bambu","identifier":"11300","activeSpool":"950","spareSpools":"0"},{"filament":"PLA Matte","baseColor":"Yellow","color":"Savannah Yellow","brand":"Polymaker","identifier":"Polyterra","activeSpool":"1000","spareSpools":"0","link":"https://a.co/d/0iz6b93I"},{"filament":"PLA Matte","baseColor":"Green","color":"Grass Green","brand":"Bambu","identifier":"11500","activeSpool":"150","spareSpools":"1"},{"filament":"PLA Matte","baseColor":"Green","color":"Dark Green","brand":"Bambu","identifier":"11501","activeSpool":"1000","spareSpools":"0"},{"filament":"PLA Matte","baseColor":"Blue","color":"Marine Blue","brand":"Bambu","identifier":"11600","activeSpool":"0","spareSpools":"1"},{"filament":"PLA Matte","baseColor":"Blue","color":"Ice Blue","brand":"Bambu","identifier":"11601","activeSpool":"600","spareSpools":"0"},{"filament":"PLA Matte","baseColor":"Blue","color":"Dark Blue","brand":"Bambu","identifier":"11602","activeSpool":"0","spareSpools":"1"},{"filament":"PLA Matte","baseColor":"Purple","color":"Lilac Purple","brand":"Bambu","identifier":"11700","activeSpool":"0","spareSpools":"1"},{"filament":"PLA Matte","baseColor":"Purple","color":"Electric Indigo","brand":"Polymaker","identifier":"Polyterra","activeSpool":"300","spareSpools":"0","link":"https://a.co/d/026FUxKJ"},{"filament":"PLA Matte","baseColor":"Pink","color":"Sakura Pink","brand":"Bambu","identifier":"11201","activeSpool":"200","spareSpools":"1"},{"filament":"PLA Matte","baseColor":"Brown","color":"Dark Brown","brand":"Bambu","identifier":"11801","activeSpool":"800","spareSpools":"0"},{"filament":"PLA Matte","baseColor":"Brown","color":"Terracotta","brand":"Bambu","identifier":"11203","activeSpool":"900","spareSpools":"0"},{"filament":"PLA Matte","baseColor":"Tan","color":"Army Beige","brand":"Polymaker","identifier":"Polyterra","activeSpool":"400","spareSpools":"0","link":"https://a.co/d/0cfYAtG1"},{"filament":"PLA Matte","baseColor":"Black","color":"Charcoal Black","brand":"Polymaker","identifier":"Polyterra","activeSpool":"800","spareSpools":"0","link":"https://a.co/d/0hy3RcSj"},{"filament":"PLA Matte","baseColor":"Black","color":"Charcoal","brand":"Bambu","identifier":"11101","activeSpool":"0","spareSpools":"1"},{"filament":"PLA Matte","baseColor":"Gray","color":"Nardo Gray","brand":"Bambu","identifier":"11104","activeSpool":"900","spareSpools":"0"},{"filament":"PLA Matte","baseColor":"White","color":"Cotton White","brand":"Polymaker","identifier":"Polyterra","activeSpool":"500","spareSpools":"0","link":"https://a.co/d/07l1vBwz"},{"filament":"PLA Matte","baseColor":"White","color":"Ivory White","brand":"Bambu","identifier":"11100","activeSpool":"0","spareSpools":"1"},{"filament":"PLA Matte","baseColor":"Multicolor","color":"Pastel Rainbow","brand":"Polymaker","identifier":"Polyterra","activeSpool":"900","spareSpools":"0","link":"https://a.co/d/0aNZ8pZa"},{"filament":"PLA Matte","baseColor":"Multicolor","color":"Spring","brand":"Polymaker","identifier":"Polyterra","activeSpool":"500","spareSpools":"0","link":"https://a.co/d/09U1dWpd"},{"filament":"PLA Sparkle","baseColor":"Black","color":"Onyx Black","brand":"Bambu","identifier":"13101","activeSpool":"0","spareSpools":"1"},{"filament":"PLA Sparkle","baseColor":"Red","color":"Crimson Red","brand":"Bambu","identifier":"13200","activeSpool":"600","spareSpools":"0"},{"filament":"PLA Sparkle","baseColor":"Yellow","color":"Classic Gold","brand":"Bambu","identifier":"13402","activeSpool":"500","spareSpools":"0"},{"filament":"PLA Sparkle","baseColor":"Purple","color":"Royal Purple","brand":"Bambu","identifier":"13700","activeSpool":"1000","spareSpools":"0"},{"filament":"PLA Wood","baseColor":"Brown","color":"Black Walnut","brand":"Bambu","identifier":"13107","activeSpool":"0","spareSpools":"1"}]